goals/__init__.py
goals/status_1.py
goals/_clique/__init__.py
goals/_clique/group/__init__.py
goals/_licenses/gpl-3.0-standalone.html
goals/_status/status.proc.py
goals-0.0.1.dist-info/METADATA
goals-0.0.1.dist-info/WHEEL
goals-0.0.1.dist-info/top_level.txt
goals-0.0.1.dist-info/RECORD
