Metadata-Version: 2.1
Name: goals
Version: 0.0.1
License: 
Requires-Dist: bracelet
Requires-Dist: carbonado
Requires-Dist: click
